ijazz/RegionalFitter.py
ijazz/ScaleAndSmearing.py
ijazz/__init__.py
ijazz/alpha_tensors.py
ijazz/categorize.py
ijazz/config.py
ijazz/dtypes.py
ijazz/plotting.py
ijazz/sas_utils.py
ijazz/toys.py
ijazz-0.1.1.dist-info/METADATA
ijazz-0.1.1.dist-info/WHEEL
ijazz-0.1.1.dist-info/entry_points.txt
ijazz-0.1.1.dist-info/top_level.txt
ijazz-0.1.1.dist-info/RECORD
