Metadata-Version: 2.4
Name: ijazz
Version: 0.1.1
Summary: I Just AnaliZe the Z 2.0
Author-email: Fabrice Couderc <fabrice.couderc@cea.fr>, Paul Gaigne <paul.gaigne@cern.ch>, Ozgur Sahin <ozgur.sahin@cern.ch>
Project-URL: Repository, https://gitlab.cern.ch/fcouderc/ijazz_2p0
Requires-Python: >=3.8
Requires-Dist: tensorflow==2.7.0
Requires-Dist: tensorflow-probability~=0.12.2
Requires-Dist: protobuf==3.20.1
Requires-Dist: numpy==1.26.4
Requires-Dist: uproot
Requires-Dist: pyyaml
Requires-Dist: pyarrow
Requires-Dist: tqdm
Requires-Dist: pandas
Requires-Dist: correctionlib
Requires-Dist: fast_histogram
Requires-Dist: cms-fstyle-PG[fitter]
